{
    "name": "Web Automation",
    "phoneNumber": "8153211010",
    "cardNumber": "4111111111111111",
    "expirationDate": "1225",
    "cvv": "333",
    "postalCode": "89123",
    "shippingName": "Web Automation",
    "shippingStreet": "1217 W Hammer Ln",
    "shippingCity": "North Las Vegas",
    "shippingPostalCode": "89123",
    "shippingState": "Nevada",
    "shippingCountry": "United States",
    "shippingPhone": "8153211010",

    "homepageVideoUrl": "/sp/fat-loss-extreme-women/fbk-cpc",
    "burnEvolvedUrl": "/sp/fat-loss-extreme/fl-burn-cs",
    "burnPmUrl": "/sp/fat-loss-extreme/fl-burn-pm-cs",
    "customDietPlanUrl": "/sp/fat-loss-extreme/fl-cdp-us",
    "vsuUrl": "sp/fat-loss-extreme/fl-vsu-us",
    "greensUrl": "/sp/survey/special-offer-coupon",
    "fatLossExtremeUrl": "/order-form/fat-loss-extreme-bundle-f-bt-f4-v3"
}
