{
    "surveyLandingPage": {
        "surveyUrl": "/sp/survey/fbk-cpc",
        "checkoutUrl": "fat-loss-extreme-bundle-bt-f3",
        "productDescription": "Fat Loss Extreme for Him $57",
        "productPrice": "$57.00 USD",
        "productBundle": [
            "Fat Loss Extreme for Him $57",
            "Six-Pack Shred",
            "Recipe Guide",
            "Big Arms Program"
        ]
    },
    "Greens": {
        "funnelUrl": "special-offer-coupon-3",
        "offerDescription": "GREENS REGULAR - DISCOUNTED",
        "offerPrice": "$42.27",
        "offerName": "GREENS REGULAR - DISCOUNTED",
        "orderQuantity": 1,
        "baseCurrencyAmount": "$39.00",
        "taxAmount": "$3.27",
        "refundableAmount": "$42.27"
    },
    "VSU": {
        "funnelUrl": "vsu-special-offer",
        "offerDescription": "VSU - Monthly 9.95 (30-Day Trial)",
        "offerPrice": "$0.00",
        "offerName": "VSU - Monthly 9.95 (30-Day Trial)",
        "orderQuantity": 1,
        "baseCurrencyAmount": "$0.00",
        "taxAmount": "$0.00",
        "refundableAmount": "$0.00"
    },
    "Burn Evolved": {
        "funnelUrl": "burn-cs-",
        "offerDescription": "BURN EVOLVED 2.0 - Monthly",
        "offerPrice": "$44.43",
        "offerName": "BURN EVOLVED 2.0 - Monthly",
        "orderQuantity": 1,
        "baseCurrencyAmount": "$41.00",
        "taxAmount": "$3.43",
        "refundableAmount": "$44.43"
    },
    "Burn PM": {
        "funnelUrl": "burn-pm-cs",
        "offerDescription": "BURN PM - Monthly",
        "offerPrice": "$44.43",
        "offerName": "BURN PM - Monthly",
        "orderQuantity": 1,
        "baseCurrencyAmount": "$41.00",
        "taxAmount": "$3.43",
        "refundableAmount": "$44.43"
    },
    "cdpFunnel": [
        "GREENS REGULAR - DISCOUNTED",
        "Custom Diet Plan - 4 weeks",
        "VSU - Monthly 9.95 (30-Day Trial)",
        "BURN PM - Monthly",
        "BURN EVOLVED 2.0 - 6-Bottle Upgrade",
        "BURN EVOLVED 2.0 - 3 bottles",
        "Fat Loss Extreme for Him $57"
    ],
    "trainerData": {
        "assignedTrainer": "Trainer Three",
        "filepath": "cypress/fixtures/uploadFile/VSCustomPlan.pdf",
        "fileName": "VSCustomPlan.pdf",
        "fileType": "pdf",
        "assignedTrainerUser": "trainer-three@example.com",
        "trainerPassw": "asdfasdf"
    },
    "firstName": "survey-fbk-cpc",
    "lastName": "cdpFunnel",
    "country": "USA",
    "address": "3722 South Las Vegas Boulevard, Suite 3502",
    "city": "Las Vegas",
    "state": "NV",
    "postalCode": "89158"
}
